zk_rn_lib_maker/__init__.py
zk_rn_lib_maker/__main__.py
zk_rn_lib_maker/version.cfg
zk_rn_lib_maker-1.0.3.dist-info/METADATA
zk_rn_lib_maker-1.0.3.dist-info/WHEEL
zk_rn_lib_maker-1.0.3.dist-info/entry_points.txt
zk_rn_lib_maker-1.0.3.dist-info/top_level.txt
zk_rn_lib_maker-1.0.3.dist-info/RECORD
